[
  {
    "id": "3",
    "uid": "",
    "title": "Wouter is raar",
    "contents": "Alleen de contents!",
    "timePublished": 1570657652401
  },
  {
    "id": 0.7901807184261516,
    "title": "This is a title"
  },
  {
    "id": "0.06986601195512443",
    "title": "This is a title"
  },
  {
    "id": "0.6987985743200826",
    "title": "This is a title"
  },
  {
    "id": "0.0886255180414166",
    "title": "This is a title"
  },
  {
    "id": "0.00394876499543706",
    "uid": "",
    "title": "Nog een blog post",
    "contents": "",
    "timePublished": 0
  },
  {
    "id": "0.6604485088006731",
    "uid": "1",
    "title": "Another Blog Post",
    "contents": "",
    "timePublished": 0
  },
  {
    "id": "0.1916178307411338",
    "uid": "1",
    "title": "Another Blog Post",
    "contents": "",
    "timePublished": 1570661881973
  },
  {
    "id": "0.5616586687572012",
    "uid": "1",
    "title": "Another Blog Post",
    "contents": "Bladiebla",
    "timePublished": 1
  },
  {
    "id": "0.5285969225538789",
    "uid": "1",
    "title": "Another Blog Post",
    "contents": "Bladiebla",
    "timePublished": 1
  },
  {
    "id": "0.7411481275061707",
    "uid": "1",
    "title": "My Blog Post",
    "contents": "Bladiebla",
    "timePublished": 1
  },
  {
    "id": "0.025818004980556974",
    "uid": "1",
    "title": "Wv Blog Post",
    "contents": "Bladiebla",
    "timePublished": 1
  },
  {
    "id": "0.8934982214963965",
    "uid": "1",
    "title": "Wv Blog Post",
    "contents": "Bladiebla",
    "timePublished": 1
  }
]